<?xml version="1.0" encoding="utf-8"?><Transactions><Terminal>6000031</Terminal><Transaction><TranNum>5700003</TranNum><JournalNum>57</JournalNum><TranDate>2014-03-03</TranDate><TranTime>10:44</TranTime><FirstAmount>398.05</FirstAmount><FinalAmount>398.05</FinalAmount><AmountBeforeVat>337.33</AmountBeforeVat><Round>0.00</Round><Vat>18.00</Vat><DiscountType>0</DiscountType><DiscountPerc>0.00</DiscountPerc><DiscountAmount>0.00</DiscountAmount><CashierID>4</CashierID><CustomerID>0965</CustomerID><Change>0.00</Change><Components><Component><CompType>2</CompType><Description>שורטס לוז 9019</Description><Code>8120000000044</Code><Department>1</Department><CFirstAmount>419.00</CFirstAmount><CMiddleAmount>398.05</CMiddleAmount><CFinalAmount>398.05</CFinalAmount><CQuantity>1.00</CQuantity><Sales></Sales><CDiscType>1</CDiscType><CAmountDiscount></CAmountDiscount><ItemDiscount>0.00</ItemDiscount><DeprtDiscount>0.000</DeprtDiscount><CPercDisc>5.00</CPercDisc><CDetails></CDetails><CRemark></CRemark></Component></Components><Payments><Cash><CashAmount></CashAmount></Cash><Credit><CreditAmount>398.05</CreditAmount><CreditBrand>6</CreditBrand><CreditCardNum>0741</CreditCardNum><CreditFirstAmount>132</CreditFirstAmount><CreditNonFirstAmount>133</CreditNonFirstAmount><CreditPaymentsNum>3</CreditPaymentsNum><CreditCurrencyType>1</CreditCurrencyType><CreditApprovalNum>33159</CreditApprovalNum></Credit></Payments></Transaction></Transactions>