<?xml version="1.0" encoding="utf-8"?><Transactions><Terminal>6000031</Terminal><Transaction><TranNum>6300001</TranNum><JournalNum>63</JournalNum><TranDate>2014-03-06</TranDate><TranTime>10:43</TranTime><FirstAmount>207.10</FirstAmount><FinalAmount>207.10</FinalAmount><AmountBeforeVat>175.51</AmountBeforeVat><Round>0.00</Round><Vat>18.00</Vat><DiscountType>0</DiscountType><DiscountPerc>0.00</DiscountPerc><DiscountAmount>0.00</DiscountAmount><CashierID>2</CashierID><CustomerID>9625</CustomerID><Change>0.00</Change><Components><Component><CompType>2</CompType><Description></Description><Code></Code><Department>0</Department><CFirstAmount>89.00</CFirstAmount><CMiddleAmount>84.55</CMiddleAmount><CFinalAmount>84.55</CFinalAmount><CQuantity>1.00</CQuantity><Sales></Sales><CDiscType>1</CDiscType><CAmountDiscount></CAmountDiscount><ItemDiscount>0.00</ItemDiscount><DeprtDiscount>0.000</DeprtDiscount><CPercDisc>5.00</CPercDisc><CDetails></CDetails><CRemark></CRemark></Component><Component><CompType>2</CompType><Description>חולצת וי שליצים</Description><Code>2830000000042</Code><Department>1</Department><CFirstAmount>129.00</CFirstAmount><CMiddleAmount>122.55</CMiddleAmount><CFinalAmount>122.55</CFinalAmount><CQuantity>1.00</CQuantity><Sales></Sales><CDiscType>1</CDiscType><CAmountDiscount></CAmountDiscount><ItemDiscount>0.00</ItemDiscount><DeprtDiscount>0.000</DeprtDiscount><CPercDisc>5.00</CPercDisc><CDetails></CDetails><CRemark></CRemark></Component></Components><Payments><Cash><CashAmount></CashAmount></Cash><Credit><CreditAmount>207.10</CreditAmount><CreditBrand>1</CreditBrand><CreditCardNum>1985</CreditCardNum><CreditFirstAmount>0</CreditFirstAmount><CreditNonFirstAmount>0</CreditNonFirstAmount><CreditPaymentsNum>0</CreditPaymentsNum><CreditCurrencyType>1</CreditCurrencyType><CreditApprovalNum>0</CreditApprovalNum></Credit></Payments></Transaction></Transactions>