<?xml version="1.0" encoding="utf-8"?><Transactions><Terminal>6000031</Terminal><Transaction><TranNum>6600001</TranNum><JournalNum>66</JournalNum><TranDate>2014-03-09</TranDate><TranTime>11:10</TranTime><FirstAmount>77.50</FirstAmount><FinalAmount>77.50</FinalAmount><AmountBeforeVat>65.68</AmountBeforeVat><Round>0.00</Round><Vat>18.00</Vat><DiscountType>0</DiscountType><DiscountPerc>0.00</DiscountPerc><DiscountAmount>0.00</DiscountAmount><CashierID>2</CashierID><CustomerID>9786</CustomerID><Change>0.00</Change><Components><Component><CompType>2</CompType><Description>מכנס לוז שרוך44600</Description><Code>2747000000002</Code><Department>1</Department><CFirstAmount>349.00</CFirstAmount><CMiddleAmount>-331.55</CMiddleAmount><CFinalAmount>-331.55</CFinalAmount><CQuantity>-1.00</CQuantity><Sales></Sales><CDiscType>1</CDiscType><CAmountDiscount></CAmountDiscount><ItemDiscount>0.00</ItemDiscount><DeprtDiscount>0.000</DeprtDiscount><CPercDisc>5.00</CPercDisc><CDetails></CDetails><CRemark></CRemark></Component><Component><CompType>2</CompType><Description>חולצת פרי1069</Description><Code>2570000000123</Code><Department>1</Department><CFirstAmount>159.00</CFirstAmount><CMiddleAmount>239.00</CMiddleAmount><CFinalAmount>239.00</CFinalAmount><CQuantity>2.00</CQuantity><Sales></Sales><CDiscType>2</CDiscType><CAmountDiscount>79.00</CAmountDiscount><ItemDiscount>0.00</ItemDiscount><DeprtDiscount>0.000</DeprtDiscount><CPercDisc></CPercDisc><CDetails></CDetails><CRemark></CRemark></Component><Component><CompType>2</CompType><Description>2569-20</Description><Code>2614000000012</Code><Department>1</Department><CFirstAmount>179.00</CFirstAmount><CMiddleAmount>170.05</CMiddleAmount><CFinalAmount>170.05</CFinalAmount><CQuantity>1.00</CQuantity><Sales></Sales><CDiscType>1</CDiscType><CAmountDiscount></CAmountDiscount><ItemDiscount>0.00</ItemDiscount><DeprtDiscount>0.000</DeprtDiscount><CPercDisc>5.00</CPercDisc><CDetails></CDetails><CRemark></CRemark></Component></Components><Payments><Cash><CashAmount></CashAmount></Cash><Credit><CreditAmount>77.50</CreditAmount><CreditBrand>1</CreditBrand><CreditCardNum>3822</CreditCardNum><CreditFirstAmount>0</CreditFirstAmount><CreditNonFirstAmount>0</CreditNonFirstAmount><CreditPaymentsNum>0</CreditPaymentsNum><CreditCurrencyType>1</CreditCurrencyType><CreditApprovalNum>0</CreditApprovalNum></Credit></Payments></Transaction></Transactions>