<?xml version="1.0" encoding="utf-8"?><Transactions><Terminal>6000031</Terminal><Transaction><TranNum>5600007</TranNum><JournalNum>56</JournalNum><TranDate>2014-03-02</TranDate><TranTime>16:43</TranTime><FirstAmount>238.50</FirstAmount><FinalAmount>238.00</FinalAmount><AmountBeforeVat>201.69</AmountBeforeVat><Round>0.00</Round><Vat>18.00</Vat><DiscountType>2</DiscountType><DiscountPerc>0.00</DiscountPerc><DiscountAmount>0.50</DiscountAmount><CashierID>4</CashierID><CustomerID>9812</CustomerID><Change>0.00</Change><Components><Component><CompType>2</CompType><Description>חולצת פרי1069</Description><Code>2570000000123</Code><Department>1</Department><CFirstAmount>159.00</CFirstAmount><CMiddleAmount>159.00</CMiddleAmount><CFinalAmount>158.67</CFinalAmount><CQuantity>1.00</CQuantity><Sales></Sales><CDiscType>0</CDiscType><CAmountDiscount></CAmountDiscount><ItemDiscount>0.00</ItemDiscount><DeprtDiscount>0.000</DeprtDiscount><CPercDisc></CPercDisc><CDetails></CDetails><CRemark></CRemark></Component><Component><CompType>2</CompType><Description>חולצה פיס יהלומ</Description><Code>2570000000140</Code><Department>1</Department><CFirstAmount>159.00</CFirstAmount><CMiddleAmount>79.50</CMiddleAmount><CFinalAmount>79.33</CFinalAmount><CQuantity>1.00</CQuantity><Sales></Sales><CDiscType>1</CDiscType><CAmountDiscount></CAmountDiscount><ItemDiscount>0.00</ItemDiscount><DeprtDiscount>0.000</DeprtDiscount><CPercDisc>50.00</CPercDisc><CDetails></CDetails><CRemark></CRemark></Component></Components><Payments><Cash><CashAmount>238.00</CashAmount></Cash></Payments></Transaction></Transactions>