<?xml version="1.0" encoding="utf-8"?><Transactions><Terminal>6000031</Terminal><Transaction><TranNum>1000005</TranNum><JournalNum>10</JournalNum><TranDate>2014-02-05</TranDate><TranTime>13:39</TranTime><FirstAmount>1613.05</FirstAmount><FinalAmount>1613.05</FinalAmount><AmountBeforeVat>1366.99</AmountBeforeVat><Round>0.00</Round><Vat>18.00</Vat><DiscountType>0</DiscountType><DiscountPerc>0.00</DiscountPerc><DiscountAmount>0.00</DiscountAmount><CashierID>4</CashierID><CustomerID>0683</CustomerID><Change>0.00</Change><Components><Component><CompType>2</CompType><Description>BOY 042</Description><Code>8120000000284</Code><Department>4</Department><CFirstAmount>599.00</CFirstAmount><CMiddleAmount>599.00</CMiddleAmount><CFinalAmount>599.00</CFinalAmount><CQuantity>1.00</CQuantity><Sales></Sales><CDiscType>0</CDiscType><CAmountDiscount></CAmountDiscount><ItemDiscount>0.00</ItemDiscount><DeprtDiscount>0.000</DeprtDiscount><CPercDisc></CPercDisc><CDetails></CDetails><CRemark></CRemark></Component><Component><CompType>2</CompType><Description>BOYFRIND BONNY</Description><Code>8120000000274</Code><Department>1</Department><CFirstAmount>599.00</CFirstAmount><CMiddleAmount>299.50</CMiddleAmount><CFinalAmount>299.50</CFinalAmount><CQuantity>1.00</CQuantity><Sales></Sales><CDiscType>1</CDiscType><CAmountDiscount></CAmountDiscount><ItemDiscount>0.00</ItemDiscount><DeprtDiscount>0.000</DeprtDiscount><CPercDisc>50.00</CPercDisc><CDetails></CDetails><CRemark></CRemark></Component><Component><CompType>2</CompType><Description>מכנס לוז עור309</Description><Code>2600118</Code><Department>1</Department><CFirstAmount>319.00</CFirstAmount><CMiddleAmount>319.00</CMiddleAmount><CFinalAmount>319.00</CFinalAmount><CQuantity>1.00</CQuantity><Sales></Sales><CDiscType>0</CDiscType><CAmountDiscount></CAmountDiscount><ItemDiscount>0.00</ItemDiscount><DeprtDiscount>0.000</DeprtDiscount><CPercDisc></CPercDisc><CDetails></CDetails><CRemark></CRemark></Component><Component><CompType>2</CompType><Description>339-1</Description><Code>2570000000049</Code><Department>4</Department><CFirstAmount>299.00</CFirstAmount><CMiddleAmount>149.50</CMiddleAmount><CFinalAmount>149.50</CFinalAmount><CQuantity>1.00</CQuantity><Sales></Sales><CDiscType>1</CDiscType><CAmountDiscount></CAmountDiscount><ItemDiscount>0.00</ItemDiscount><DeprtDiscount>0.000</DeprtDiscount><CPercDisc>50.00</CPercDisc><CDetails></CDetails><CRemark></CRemark></Component><Component><CompType>2</CompType><Description>איטליה 259</Description><Code>2600168</Code><Department>8</Department><CFirstAmount>259.00</CFirstAmount><CMiddleAmount>246.05</CMiddleAmount><CFinalAmount>246.05</CFinalAmount><CQuantity>1.00</CQuantity><Sales></Sales><CDiscType>1</CDiscType><CAmountDiscount></CAmountDiscount><ItemDiscount>0.00</ItemDiscount><DeprtDiscount>0.000</DeprtDiscount><CPercDisc>5.00</CPercDisc><CDetails></CDetails><CRemark></CRemark></Component></Components><Payments><Cash><CashAmount></CashAmount></Cash><Credit><CreditAmount>1613.05</CreditAmount><CreditBrand>1</CreditBrand><CreditCardNum>6698</CreditCardNum><CreditFirstAmount>806</CreditFirstAmount><CreditNonFirstAmount>807</CreditNonFirstAmount><CreditPaymentsNum>2</CreditPaymentsNum><CreditCurrencyType>1</CreditCurrencyType><CreditApprovalNum>4857964</CreditApprovalNum></Credit></Payments></Transaction></Transactions>