<?xml version="1.0" encoding="utf-8"?><Transactions><Terminal>6000031</Terminal><Transaction><TranNum>6000014</TranNum><JournalNum>60</JournalNum><TranDate>2014-03-04</TranDate><TranTime>20:07</TranTime><FirstAmount>207.90</FirstAmount><FinalAmount>207.90</FinalAmount><AmountBeforeVat>176.19</AmountBeforeVat><Round>0.00</Round><Vat>18.00</Vat><DiscountType>0</DiscountType><DiscountPerc>0.00</DiscountPerc><DiscountAmount>0.00</DiscountAmount><CashierID>4</CashierID><CustomerID>9891</CustomerID><Change>0.00</Change><Components><Component><CompType>2</CompType><Description>גופיה היינס</Description><Code>60013</Code><Department>2</Department><CFirstAmount>29.00</CFirstAmount><CMiddleAmount>40.60</CMiddleAmount><CFinalAmount>40.60</CFinalAmount><CQuantity>2.00</CQuantity><Sales></Sales><CDiscType>1</CDiscType><CAmountDiscount></CAmountDiscount><ItemDiscount>0.00</ItemDiscount><DeprtDiscount>0.000</DeprtDiscount><CPercDisc>30.00</CPercDisc><CDetails></CDetails><CRemark></CRemark></Component><Component><CompType>2</CompType><Description>טוניקה V בגב</Description><Code>9290000000094</Code><Department>1</Department><CFirstAmount>239.00</CFirstAmount><CMiddleAmount>167.30</CMiddleAmount><CFinalAmount>167.30</CFinalAmount><CQuantity>1.00</CQuantity><Sales></Sales><CDiscType>1</CDiscType><CAmountDiscount></CAmountDiscount><ItemDiscount>0.00</ItemDiscount><DeprtDiscount>0.000</DeprtDiscount><CPercDisc>30.00</CPercDisc><CDetails></CDetails><CRemark></CRemark></Component></Components><Payments><Cash><CashAmount></CashAmount></Cash><Credit><CreditAmount>207.90</CreditAmount><CreditBrand>1</CreditBrand><CreditCardNum>9380</CreditCardNum><CreditFirstAmount>0</CreditFirstAmount><CreditNonFirstAmount>0</CreditNonFirstAmount><CreditPaymentsNum>0</CreditPaymentsNum><CreditCurrencyType>1</CreditCurrencyType><CreditApprovalNum>6645030</CreditApprovalNum></Credit></Payments></Transaction></Transactions>