<?xml version="1.0" encoding="utf-8"?><Transactions><Terminal>6000031</Terminal><Transaction><TranNum>5800006</TranNum><JournalNum>58</JournalNum><TranDate>2014-03-03</TranDate><TranTime>17:59</TranTime><FirstAmount>137.75</FirstAmount><FinalAmount>137.75</FinalAmount><AmountBeforeVat>116.74</AmountBeforeVat><Round>0.00</Round><Vat>18.00</Vat><DiscountType>0</DiscountType><DiscountPerc>0.00</DiscountPerc><DiscountAmount>0.00</DiscountAmount><CashierID>7</CashierID><CustomerID></CustomerID><Change>0.00</Change><Components><Component><CompType>2</CompType><Description>גופיה קלאסית</Description><Code>2830000000054</Code><Department>2</Department><CFirstAmount>29.00</CFirstAmount><CMiddleAmount>137.75</CMiddleAmount><CFinalAmount>137.75</CFinalAmount><CQuantity>5.00</CQuantity><Sales></Sales><CDiscType>1</CDiscType><CAmountDiscount></CAmountDiscount><ItemDiscount>0.00</ItemDiscount><DeprtDiscount>0.000</DeprtDiscount><CPercDisc>5.00</CPercDisc><CDetails></CDetails><CRemark></CRemark></Component></Components><Payments><Cash><CashAmount></CashAmount></Cash><Credit><CreditAmount>137.75</CreditAmount><CreditBrand>1</CreditBrand><CreditCardNum>0399</CreditCardNum><CreditFirstAmount>0</CreditFirstAmount><CreditNonFirstAmount>0</CreditNonFirstAmount><CreditPaymentsNum>0</CreditPaymentsNum><CreditCurrencyType>1</CreditCurrencyType><CreditApprovalNum>0</CreditApprovalNum></Credit></Payments></Transaction></Transactions>